kyly.py
kyly-0.3.dist-info/LICENSE.txt
kyly-0.3.dist-info/METADATA
kyly-0.3.dist-info/WHEEL
kyly-0.3.dist-info/top_level.txt
kyly-0.3.dist-info/RECORD
