Metadata-Version: 2.1
Name: kyly
Version: 0.3
Summary: Simple API wrapper for bit.ly
Home-page: UNKNOWN
Author: Siddhant Kumar
License: UNKNOWN
Platform: UNKNOWN
Classifier: Programming Language :: Python :: 3
Classifier: License :: OSI Approved :: MIT License
Classifier: Operating System :: OS Independent
Requires-Python: >=3.5
License-File: LICENSE.txt
